pyams_auth_azure/__init__.py
pyams_auth_azure/include.py
pyams_auth_azure/interfaces.py
pyams_auth_azure/plugin.py
pyams_auth_azure/doctests/README.rst
pyams_auth_azure/locales/pyams_auth_azure.pot
pyams_auth_azure/locales/fr/LC_MESSAGES/pyams_auth_azure.mo
pyams_auth_azure/locales/fr/LC_MESSAGES/pyams_auth_azure.po
pyams_auth_azure/zmi/__init__.py
pyams_auth_azure/zmi/plugin.py
pyams_auth_azure-2.0.2.dist-info/LICENSE
pyams_auth_azure-2.0.2.dist-info/METADATA
pyams_auth_azure-2.0.2.dist-info/WHEEL
pyams_auth_azure-2.0.2.dist-info/namespace_packages.txt
pyams_auth_azure-2.0.2.dist-info/top_level.txt
pyams_auth_azure-2.0.2.dist-info/RECORD
